README.md
setup.py
dawn/__init__.py
dawn/epub.py
dawn/epub2.py
dawn/epub3.py
dawn/open.py
dawn/utils.py
dawn.egg-info/PKG-INFO
dawn.egg-info/SOURCES.txt
dawn.egg-info/dependency_links.txt
dawn.egg-info/requires.txt
dawn.egg-info/top_level.txt