Metadata-Version: 1.1
Name: dawn
Version: 0.6.0
Summary: Open and modify ePubs
Home-page: http://git.glose.com/opensource/dawn
Author: Arthur Darcet
Author-email: hello+dawn@glose.com
License: MIT
Platform: UNKNOWN
Classifier: Development Status :: 4 - Beta
Classifier: Intended Audience :: Developers
Classifier: License :: OSI Approved :: MIT License
Classifier: Operating System :: OS Independent
Classifier: Programming Language :: Python
Classifier: Programming Language :: Python :: 3.6
Classifier: Programming Language :: Python :: 3.7
Classifier: Topic :: Software Development :: Libraries :: Python Modules
